{
  "resourceType": "ValueSet",
  "id": "nachc-g2-de79",
  "url": "http://fhir.org/guides/nachc/hiv-cds/ValueSet/nachc-g2-de79",
  "name": "TenofovirDisoproxilFumarateTDF300mgSuppliedChoices",
  "title": "Tenofovir Disoproxil Fumarate (TDF) 300mg Supplied Choices",
  "status": "draft",
  "experimental": false,
  "description": "Codes representing possible values for the Tenofovir Disoproxil Fumarate (TDF) 300mg Supplied Choices element",
  "immutable": true,
  "compose": {
    "include": [ {
      "system": "http://fhir.org/guides/nachc/hiv-cds/CodeSystem/hiv-custom",
      "concept": [ {
        "code": "NACHC.G2.DE79",
        "display": "0093-7104"
      }, {
        "code": "NACHC.G2.DE80",
        "display": "0904-6821"
      }, {
        "code": "NACHC.G2.DE81",
        "display": "16714-820"
      }, {
        "code": "NACHC.G2.DE82",
        "display": "24236-284"
      }, {
        "code": "NACHC.G2.DE83",
        "display": "31722-535"
      }, {
        "code": "NACHC.G2.DE84",
        "display": "33342-096"
      }, {
        "code": "NACHC.G2.DE85",
        "display": "42291-800"
      }, {
        "code": "NACHC.G2.DE86",
        "display": "42385-901"
      }, {
        "code": "NACHC.G2.DE87",
        "display": "50090-0754"
      }, {
        "code": "NACHC.G2.DE88",
        "display": "50268-758"
      }, {
        "code": "NACHC.G2.DE89",
        "display": "53808-0810"
      }, {
        "code": "NACHC.G2.DE90",
        "display": "53808-1128"
      }, {
        "code": "NACHC.G2.DE91",
        "display": "54569-5334"
      }, {
        "code": "NACHC.G2.DE92",
        "display": "55154-4426"
      }, {
        "code": "NACHC.G2.DE93",
        "display": "60505-4666"
      }, {
        "code": "NACHC.G2.DE94",
        "display": "60687-366"
      }, {
        "code": "NACHC.G2.DE95",
        "display": "61958-0401"
      }, {
        "code": "NACHC.G2.DE96",
        "display": "64380-714"
      }, {
        "code": "NACHC.G2.DE97",
        "display": "65862-421"
      }, {
        "code": "NACHC.G2.DE98",
        "display": "67184-0521"
      }, {
        "code": "NACHC.G2.DE99",
        "display": "69025-103"
      }, {
        "code": "NACHC.G2.DE100",
        "display": "69076-105"
      }, {
        "code": "NACHC.G2.DE101",
        "display": "69097-533"
      }, {
        "code": "NACHC.G2.DE102",
        "display": "69189-0401"
      }, {
        "code": "NACHC.G2.DE103",
        "display": "70518-0546"
      }, {
        "code": "NACHC.G2.DE104",
        "display": "70518-0918"
      }, {
        "code": "NACHC.G2.DE105",
        "display": "70518-1002"
      }, {
        "code": "NACHC.G2.DE106",
        "display": "70518-2151"
      } ]
    } ]
  }
}