{
  "resourceType": "ValueSet",
  "id": "patient-encounter-choices",
  "url": "http://fhir.org/guides/nachc/hiv-cds/ValueSet/patient-encounter-choices",
  "name": "patient-encounter-choices",
  "title": "Patient Encounter Choices",
  "status": "draft",
  "experimental": false,
  "description": "Codes representing possible values for the Patient Encounter Choices element",
  "immutable": true,
  "compose": {
    "include": [ {
      "system": "http://fhir.org/guides/nachc/hiv-cds/CodeSystem/hiv-custom",
      "concept": [ {
        "code": "Patient Encounter-99202",
        "display": "99202"
      }, {
        "code": "Patient Encounter-99203",
        "display": "99203"
      }, {
        "code": "Patient Encounter-99204",
        "display": "99204"
      }, {
        "code": "Patient Encounter-99205",
        "display": "99205"
      }, {
        "code": "Patient Encounter-99212",
        "display": "99212"
      }, {
        "code": "Patient Encounter-99213",
        "display": "99213"
      }, {
        "code": "Patient Encounter-99214",
        "display": "99214"
      }, {
        "code": "Patient Encounter-99215",
        "display": "99215"
      }, {
        "code": "Patient Encounter-99218",
        "display": "99218"
      }, {
        "code": "Patient Encounter-99219",
        "display": "99219"
      }, {
        "code": "Patient Encounter-99220",
        "display": "99220"
      }, {
        "code": "Patient Encounter-99221",
        "display": "99221"
      }, {
        "code": "Patient Encounter-99222",
        "display": "99222"
      }, {
        "code": "Patient Encounter-99223",
        "display": "99223"
      }, {
        "code": "Patient Encounter-99231",
        "display": "99231"
      }, {
        "code": "Patient Encounter-99232",
        "display": "99232"
      }, {
        "code": "Patient Encounter-99233",
        "display": "99233"
      }, {
        "code": "Patient Encounter-99234",
        "display": "99234"
      }, {
        "code": "Patient Encounter-99235",
        "display": "99235"
      }, {
        "code": "Patient Encounter-99236",
        "display": "99236"
      }, {
        "code": "Patient Encounter-99291",
        "display": "99291"
      }, {
        "code": "Patient Encounter-99304",
        "display": "99304"
      }, {
        "code": "Patient Encounter-99305",
        "display": "99305"
      }, {
        "code": "Patient Encounter-99306",
        "display": "99306"
      }, {
        "code": "Patient Encounter-99307",
        "display": "99307"
      }, {
        "code": "Patient Encounter-99308",
        "display": "99308"
      }, {
        "code": "Patient Encounter-99309",
        "display": "99309"
      }, {
        "code": "Patient Encounter-99310",
        "display": "99310"
      }, {
        "code": "Patient Encounter-99324",
        "display": "99324"
      }, {
        "code": "Patient Encounter-99325",
        "display": "99325"
      }, {
        "code": "Patient Encounter-99326",
        "display": "99326"
      }, {
        "code": "Patient Encounter-99327",
        "display": "99327"
      }, {
        "code": "Patient Encounter-99328",
        "display": "99328"
      }, {
        "code": "Patient Encounter-99334",
        "display": "99334"
      }, {
        "code": "Patient Encounter-99335",
        "display": "99335"
      }, {
        "code": "Patient Encounter-99336",
        "display": "99336"
      }, {
        "code": "Patient Encounter-99337",
        "display": "99337"
      }, {
        "code": "Patient Encounter-99341",
        "display": "99341"
      }, {
        "code": "Patient Encounter-99342",
        "display": "99342"
      }, {
        "code": "Patient Encounter-99343",
        "display": "99343"
      }, {
        "code": "Patient Encounter-99344",
        "display": "99344"
      }, {
        "code": "Patient Encounter-99345",
        "display": "99345"
      }, {
        "code": "Patient Encounter-99347",
        "display": "99347"
      }, {
        "code": "Patient Encounter-99348",
        "display": "99348"
      }, {
        "code": "Patient Encounter-99349",
        "display": "99349"
      }, {
        "code": "Patient Encounter-99350",
        "display": "99350"
      } ]
    } ]
  }
}