{
  "resourceType": "ValueSet",
  "id": "nachc-a1-de2",
  "url": "http://fhir.org/guides/nachc/hiv-cds/ValueSet/nachc-a1-de2",
  "name": "HIVinfectionasaconditionChoices",
  "title": "HIV infection as a condition Choices",
  "status": "draft",
  "experimental": false,
  "description": "Codes representing possible values for the HIV infection as a condition Choices element",
  "immutable": true,
  "compose": {
    "include": [ {
      "system": "http://fhir.org/guides/nachc/hiv-cds/CodeSystem/hiv-custom",
      "concept": [ {
        "code": "NACHC.A1.DE2",
        "display": "Acquired hemolytic anemia co-occurrent with human immunodeficiency virus infection (disorder)"
      }, {
        "code": "NACHC.A1.DE3",
        "display": "Acquired immune deficiency syndrome (disorder)"
      }, {
        "code": "NACHC.A1.DE4",
        "display": "Acquired immune deficiency syndrome-related nephropathy (disorder)"
      }, {
        "code": "NACHC.A1.DE5",
        "display": "Acquired immunodeficiency syndrome-associated disorder (disorder)"
      }, {
        "code": "NACHC.A1.DE6",
        "display": "Acute endocarditis co-occurrent with human immunodeficiency virus infection (disorder)"
      }, {
        "code": "NACHC.A1.DE7",
        "display": "Acute human immunodeficiency virus infection (disorder)"
      }, {
        "code": "NACHC.A1.DE8",
        "display": "Agranulocytosis co-occurrent with human immunodeficiency virus infection (disorder)"
      }, {
        "code": "NACHC.A1.DE9",
        "display": "Anemia co-occurrent with human immunodeficiency virus infection (disorder)"
      }, {
        "code": "NACHC.A1.DE10",
        "display": "Aplastic anemia co-occurrent with human immunodeficiency virus infection (disorder)"
      }, {
        "code": "NACHC.A1.DE11",
        "display": "Asymptomatic human immunodeficiency virus [HIV] infection status"
      }, {
        "code": "NACHC.A1.DE12",
        "display": "Asymptomatic human immunodeficiency virus A1 infection (disorder)"
      }, {
        "code": "NACHC.A1.DE13",
        "display": "Asymptomatic human immunodeficiency virus A2 infection (disorder)"
      }, {
        "code": "NACHC.A1.DE14",
        "display": "Asymptomatic human immunodeficiency virus infection (disorder)"
      }, {
        "code": "NACHC.A1.DE15",
        "display": "Asymptomatic human immunodeficiency virus infection in pregnancy (disorder)"
      }, {
        "code": "NACHC.A1.DE16",
        "display": "Bacterial pneumonia co-occurrent with human immunodeficiency virus infection (disorder)"
      }, {
        "code": "NACHC.A1.DE17",
        "display": "Burkitt lymphoma co-occurrent with human immunodeficiency virus infection (disorder)"
      }, {
        "code": "NACHC.A1.DE18",
        "display": "Candidiasis of esophagus co-occurrent with human immunodeficiency virus infection (disorder)"
      }, {
        "code": "NACHC.A1.DE19",
        "display": "Candidiasis of mouth co-occurrent with human immunodeficiency virus infection (disorder)"
      }, {
        "code": "NACHC.A1.DE20",
        "display": "Cardiomyopathy co-occurrent with human immunodeficiency virus infection (disorder)"
      }, {
        "code": "NACHC.A1.DE21",
        "display": "Chronic infection caused by herpes simplex virus co-occurrent with human immunodeficiency virus infection (disorder)"
      }, {
        "code": "NACHC.A1.DE22",
        "display": "Congenital acquired immune deficiency syndrome (disorder)"
      }, {
        "code": "NACHC.A1.DE23",
        "display": "Congenital human immunodeficiency virus infection (disorder)"
      }, {
        "code": "NACHC.A1.DE24",
        "display": "Dementia co-occurrent with human immunodeficiency virus infection (disorder)"
      }, {
        "code": "NACHC.A1.DE25",
        "display": "Demyelinating disease of central nervous system co-occurrent with human immunodeficiency virus infection (disorder)"
      }, {
        "code": "NACHC.A1.DE26",
        "display": "Diffuse non-Hodgkin immunoblastic lymphoma co-occurrent with human immunodeficiency virus infection (disorder)"
      }, {
        "code": "NACHC.A1.DE27",
        "display": "Disorder of central nervous system co-occurrent with human immunodeficiency virus infection (disorder)"
      }, {
        "code": "NACHC.A1.DE28",
        "display": "Disorder of eye proper co-occurrent with human immunodeficiency virus infection (disorder)"
      }, {
        "code": "NACHC.A1.DE29",
        "display": "Disorder of gastrointestinal tract co-occurrent with human immunodeficiency virus infection (disorder)"
      }, {
        "code": "NACHC.A1.DE30",
        "display": "Disorder of kidney co-occurrent with human immunodeficiency virus infection (disorder)"
      }, {
        "code": "NACHC.A1.DE31",
        "display": "Disorder of peripheral nervous system co-occurrent with human immunodeficiency virus infection (disorder)"
      }, {
        "code": "NACHC.A1.DE32",
        "display": "Disorder of respiratory system co-occurrent with human immunodeficiency virus infection (disorder)"
      }, {
        "code": "NACHC.A1.DE33",
        "display": "Disorder of skin co-occurrent with human immunodeficiency virus infection (disorder)"
      }, {
        "code": "NACHC.A1.DE34",
        "display": "Disorder of spinal cord co-occurrent with human immunodeficiency virus infection (disorder)"
      }, {
        "code": "NACHC.A1.DE35",
        "display": "Disseminated atypical infection caused by Mycobacterium co-occurrent with human immunodeficiency virus infection (disorder)"
      }, {
        "code": "NACHC.A1.DE36",
        "display": "Disseminated infection caused by Strongyloides co-occurrent with human immunodeficiency virus infection (disorder)"
      }, {
        "code": "NACHC.A1.DE37",
        "display": "Enlargement of liver co-occurrent with human immunodeficiency virus infection (disorder)"
      }, {
        "code": "NACHC.A1.DE38",
        "display": "Eruption of skin co-occurrent with human immunodeficiency virus infection (disorder)"
      }, {
        "code": "NACHC.A1.DE39",
        "display": "Extrapulmonary tuberculosis co-occurrent with human immunodeficiency virus infection (disorder)"
      }, {
        "code": "NACHC.A1.DE40",
        "display": "Focal segmental glomerulosclerosis co-occurrent with human immunodeficiency virus infection (disorder)"
      }, {
        "code": "NACHC.A1.DE41",
        "display": "Gastrointestinal malabsorption syndrome co-occurrent with human immunodeficiency virus infection (disorder)"
      }, {
        "code": "NACHC.A1.DE42",
        "display": "Hairy leukoplakia of tongue associated with human immunodeficiency virus disease (disorder)"
      }, {
        "code": "NACHC.A1.DE43",
        "display": "Heart disease co-occurrent with human immunodeficiency virus infection (disorder)"
      }, {
        "code": "NACHC.A1.DE44",
        "display": "Hemophagocytic syndrome co-occurrent with human immunodeficiency virus infection (disorder)"
      }, {
        "code": "NACHC.A1.DE45",
        "display": "Hepatitis B associated with Human immunodeficiency virus infection (disorder)"
      }, {
        "code": "NACHC.A1.DE46",
        "display": "Human immunodeficiency virus (HIV) II infection category B1 (disorder)"
      }, {
        "code": "NACHC.A1.DE47",
        "display": "Human immunodeficiency virus (HIV) II infection category B2 (disorder)"
      }, {
        "code": "NACHC.A1.DE48",
        "display": "Human immunodeficiency virus [HIV] disease"
      }, {
        "code": "NACHC.A1.DE49",
        "display": "Human immunodeficiency virus [HIV] disease complicating childbirth"
      }, {
        "code": "NACHC.A1.DE50",
        "display": "Human immunodeficiency virus [HIV] disease complicating pregnancy, first trimester"
      }, {
        "code": "NACHC.A1.DE51",
        "display": "Human immunodeficiency virus [HIV] disease complicating pregnancy, second trimester"
      }, {
        "code": "NACHC.A1.DE52",
        "display": "Human immunodeficiency virus [HIV] disease complicating pregnancy, third trimester"
      }, {
        "code": "NACHC.A1.DE53",
        "display": "Human immunodeficiency virus [HIV] disease complicating pregnancy, unspecified trimester"
      }, {
        "code": "NACHC.A1.DE54",
        "display": "Human immunodeficiency virus [HIV] disease complicating the puerperium"
      }, {
        "code": "NACHC.A1.DE55",
        "display": "Human immunodeficiency virus encephalitis (disorder)"
      }, {
        "code": "NACHC.A1.DE56",
        "display": "Human immunodeficiency virus encephalopathy (disorder)"
      }, {
        "code": "NACHC.A1.DE57",
        "display": "Human immunodeficiency virus enteropathy (disorder)"
      }, {
        "code": "NACHC.A1.DE58",
        "display": "Human immunodeficiency virus I infection (disorder)"
      }, {
        "code": "NACHC.A1.DE59",
        "display": "Human immunodeficiency virus II infection (disorder)"
      }, {
        "code": "NACHC.A1.DE60",
        "display": "Human immunodeficiency virus in mother complicating childbirth (disorder)"
      }, {
        "code": "NACHC.A1.DE61",
        "display": "Human immunodeficiency virus infection (disorder)"
      }, {
        "code": "NACHC.A1.DE62",
        "display": "Human immunodeficiency virus infection constitutional disease (disorder)"
      }, {
        "code": "NACHC.A1.DE63",
        "display": "Human immunodeficiency virus infection with acute lymphadenitis (disorder)"
      }, {
        "code": "NACHC.A1.DE64",
        "display": "Human immunodeficiency virus infection with aseptic meningitis (disorder)"
      }, {
        "code": "NACHC.A1.DE65",
        "display": "Human immunodeficiency virus infection with infectious mononucleosis-like syndrome (disorder)"
      }, {
        "code": "NACHC.A1.DE66",
        "display": "Human immunodeficiency virus infection with neurological disease (disorder)"
      }, {
        "code": "NACHC.A1.DE67",
        "display": "Human immunodeficiency virus infection with secondary clinical infectious disease (disorder)"
      }, {
        "code": "NACHC.A1.DE68",
        "display": "Human immunodeficiency virus leukoencephalopathy (disorder)"
      }, {
        "code": "NACHC.A1.DE69",
        "display": "Human immunodeficiency virus myopathy (disorder)"
      }, {
        "code": "NACHC.A1.DE70",
        "display": "Human immunodeficiency virus, type 2 [HIV 2] as the cause of diseases classified elsewhere"
      }, {
        "code": "NACHC.A1.DE71",
        "display": "Human immunodeficiency virus-associated periodontitis (disorder)"
      }, {
        "code": "NACHC.A1.DE72",
        "display": "Human immunodeficiency virus-related sclerosing cholangitis (disorder)"
      }, {
        "code": "NACHC.A1.DE73",
        "display": "Immune reconstitution inflammatory syndrome caused by human immunodeficiency virus infection (disorder)"
      }, {
        "code": "NACHC.A1.DE74",
        "display": "Infection caused by Aspergillus co-occurrent with human immunodeficiency virus infection (disorder)"
      }, {
        "code": "NACHC.A1.DE75",
        "display": "Infection caused by Coccidia co-occurrent with human immunodeficiency virus infection (disorder)"
      }, {
        "code": "NACHC.A1.DE76",
        "display": "Infection caused by Cryptosporidium co-occurrent with human immunodeficiency virus infection (disorder)"
      }, {
        "code": "NACHC.A1.DE77",
        "display": "Infection caused by Cytomegalovirus co-occurrent with human immunodeficiency virus infection (disorder)"
      }, {
        "code": "NACHC.A1.DE78",
        "display": "Infection caused by Dermatophyte co-occurrent with human immunodeficiency virus infection (disorder)"
      }, {
        "code": "NACHC.A1.DE79",
        "display": "Infection caused by herpes simplex virus co-occurrent with human immunodeficiency virus infection (disorder)"
      }, {
        "code": "NACHC.A1.DE80",
        "display": "Infection caused by herpes zoster virus co-occurrent with human immunodeficiency virus infection (disorder)"
      }, {
        "code": "NACHC.A1.DE81",
        "display": "Infection caused by Microsporidia co-occurrent with human immunodeficiency virus infection (disorder)"
      }, {
        "code": "NACHC.A1.DE82",
        "display": "Infection caused by Nocardia co-occurrent with human immunodeficiency virus infection (disorder)"
      }, {
        "code": "NACHC.A1.DE83",
        "display": "Infection caused by Pneumocystis co-occurrent with human immunodeficiency virus infection (disorder)"
      }, {
        "code": "NACHC.A1.DE84",
        "display": "Infection caused by Salmonella co-occurrent with human immunodeficiency virus infection (disorder)"
      }, {
        "code": "NACHC.A1.DE85",
        "display": "Infection caused by Strongyloides co-occurrent with human immunodeficiency virus infection (disorder)"
      }, {
        "code": "NACHC.A1.DE86",
        "display": "Infectious gastroenteritis co-occurrent with human immunodeficiency virus infection (disorder)"
      }, {
        "code": "NACHC.A1.DE87",
        "display": "Infective arthritis co-occurrent with human immunodeficiency virus infection (disorder)"
      }, {
        "code": "NACHC.A1.DE88",
        "display": "Invasive carcinoma of uterine cervix co-occurrent with human immunodeficiency virus infection (disorder)"
      }, {
        "code": "NACHC.A1.DE89",
        "display": "Isosporiasis co-occurrent with human immunodeficiency virus infection (disorder)"
      }, {
        "code": "NACHC.A1.DE90",
        "display": "Leukoplakia of tongue associated with human immunodeficiency virus disease (disorder)"
      }, {
        "code": "NACHC.A1.DE91",
        "display": "Lymphadenopathy co-occurrent with human immunodeficiency virus infection (disorder)"
      }, {
        "code": "NACHC.A1.DE92",
        "display": "Malignant neoplastic disease co-occurrent with human immunodeficiency virus infection (disorder)"
      }, {
        "code": "NACHC.A1.DE93",
        "display": "Multidermatomal infection caused by Herpes zoster co-occurrent with human immunodeficiency virus infection (disorder)"
      }, {
        "code": "NACHC.A1.DE94",
        "display": "Myelitis co-occurrent with human immunodeficiency virus infection (disorder)"
      }, {
        "code": "NACHC.A1.DE95",
        "display": "Myocarditis co-occurrent with human immunodeficiency virus infection (disorder)"
      }, {
        "code": "NACHC.A1.DE96",
        "display": "Nephrotic syndrome co-occurrent with human immunodeficiency virus infection (disorder)"
      }, {
        "code": "NACHC.A1.DE97",
        "display": "Neuralgia co-occurrent with human immunodeficiency virus infection (disorder)"
      }, {
        "code": "NACHC.A1.DE98",
        "display": "Neuritis co-occurrent with human immunodeficiency virus infection (disorder)"
      }, {
        "code": "NACHC.A1.DE99",
        "display": "Neuropathy caused by human immunodeficiency virus (disorder)"
      }, {
        "code": "NACHC.A1.DE100",
        "display": "Non-Hodgkin lymphoma associated with Human immunodeficiency virus infection (disorder)"
      }, {
        "code": "NACHC.A1.DE101",
        "display": "Opportunistic mycosis co-occurrent with human immunodeficiency virus infection (disorder)"
      }, {
        "code": "NACHC.A1.DE102",
        "display": "Oral hairy leukoplakia associated with human immunodeficiency virus disease (disorder)"
      }, {
        "code": "NACHC.A1.DE103",
        "display": "Organic brain syndrome co-occurrent with human immunodeficiency virus infection (disorder)"
      }, {
        "code": "NACHC.A1.DE104",
        "display": "Pediatric human immunodeficiency virus infection (disorder)"
      }, {
        "code": "NACHC.A1.DE105",
        "display": "Polyneuropathy co-occurrent with human immunodeficiency virus infection (disorder)"
      }, {
        "code": "NACHC.A1.DE106",
        "display": "Presenile dementia co-occurrent with human immunodeficiency virus infection (disorder)"
      }, {
        "code": "NACHC.A1.DE107",
        "display": "Primary cerebral lymphoma co-occurrent with human immunodeficiency virus infection (disorder)"
      }, {
        "code": "NACHC.A1.DE108",
        "display": "Progressive multifocal leukoencephalopathy co-occurrent with human immunodeficiency virus infection (disorder)"
      }, {
        "code": "NACHC.A1.DE109",
        "display": "Pyrexia of unknown origin co-occurrent with human immunodeficiency virus infection (disorder)"
      }, {
        "code": "NACHC.A1.DE110",
        "display": "Radiculitis co-occurrent with human immunodeficiency virus infection (disorder)"
      }, {
        "code": "NACHC.A1.DE111",
        "display": "Recurrent bacterial pneumonia co-occurrent with human immunodeficiency virus infection (disorder)"
      }, {
        "code": "NACHC.A1.DE112",
        "display": "Recurrent salmonella sepsis co-occurrent with human immunodeficiency virus infection (disorder)"
      }, {
        "code": "NACHC.A1.DE113",
        "display": "Renal failure syndrome co-occurrent with human immunodeficiency virus infection (disorder)"
      }, {
        "code": "NACHC.A1.DE114",
        "display": "Reticulosarcoma co-occurrent with human immunodeficiency virus infection (disorder)"
      }, {
        "code": "NACHC.A1.DE115",
        "display": "Splenomegaly co-occurrent with human immunodeficiency virus infection (disorder)"
      }, {
        "code": "NACHC.A1.DE116",
        "display": "Subacute adenoviral encephalitis co-occurrent with human immunodeficiency virus infection (disorder)"
      }, {
        "code": "NACHC.A1.DE117",
        "display": "Symptomatic human immunodeficiency virus infection (disorder)"
      }, {
        "code": "NACHC.A1.DE118",
        "display": "Visual impairment co-occurrent with human immunodeficiency virus infection (disorder)"
      } ]
    } ]
  }
}